mindspore_serving/.commit_id
mindspore_serving/__init__.py
mindspore_serving/_mindspore_serving.cpython-39-aarch64-linux-gnu.so
mindspore_serving/default_config.py
mindspore_serving/log.py
mindspore_serving/version.py
mindspore_serving/client/__init__.py
mindspore_serving/client/python/__init__.py
mindspore_serving/client/python/client.py
mindspore_serving/lib/libmindspore_serving_address_sorting.so.15
mindspore_serving/lib/libmindspore_serving_glog.so.0
mindspore_serving/lib/libmindspore_serving_gpr.so.15
mindspore_serving/lib/libmindspore_serving_grpc++.so.1
mindspore_serving/lib/libmindspore_serving_grpc.so.15
mindspore_serving/lib/libmindspore_serving_upb.so.15
mindspore_serving/lib/libserving_ascend.so
mindspore_serving/lib/libserving_common.so
mindspore_serving/proto/ms_service_pb2.py
mindspore_serving/proto/ms_service_pb2_grpc.py
mindspore_serving/server/__init__.py
mindspore_serving/server/_servable_common.py
mindspore_serving/server/_servable_local.py
mindspore_serving/server/_server.py
mindspore_serving/server/start_extra_worker.py
mindspore_serving/server/start_worker.py
mindspore_serving/server/common/__init__.py
mindspore_serving/server/common/check_type.py
mindspore_serving/server/common/decorator.py
mindspore_serving/server/common/utils.py
mindspore_serving/server/distributed/__init__.py
mindspore_serving/server/distributed/_distributed.py
mindspore_serving/server/distributed/_servable_distributed.py
mindspore_serving/server/distributed/start_distributed_worker.py
mindspore_serving/server/master/__init__.py
mindspore_serving/server/master/_master.py
mindspore_serving/server/master/context.py
mindspore_serving/server/register/__init__.py
mindspore_serving/server/register/method.py
mindspore_serving/server/register/model.py
mindspore_serving/server/register/stage_function.py
mindspore_serving/server/register/utils.py
mindspore_serving/server/worker/__init__.py
mindspore_serving/server/worker/_worker.py
mindspore_serving/server/worker/check_version.py
mindspore_serving-2.0.2.dist-info/METADATA
mindspore_serving-2.0.2.dist-info/WHEEL
mindspore_serving-2.0.2.dist-info/top_level.txt
mindspore_serving-2.0.2.dist-info/RECORD
